easipy/__init__.py
easipy/easing.py
easipy-0.0.1.dist-info/LICENSE
easipy-0.0.1.dist-info/METADATA
easipy-0.0.1.dist-info/WHEEL
easipy-0.0.1.dist-info/RECORD
